[
    {
        "ID": 1771425,
        "Name": "他在日暮之西",
        "Popularity": 178559.45,
        "Collection": 301,
        "Timestamp": "2025-03-05 03:23:23"
    },
    {
        "ID": 1712845,
        "Name": "校园歌手",
        "Popularity": 14082.52,
        "Collection": 18,
        "Timestamp": "2025-03-05 03:23:25"
    },
    {
        "ID": 1712177,
        "Name": "献我",
        "Popularity": 127629305.2,
        "Collection": 123422,
        "Timestamp": "2025-03-05 03:23:26"
    },
    {
        "ID": 1173557,
        "Name": "短篇",
        "Popularity": 1321529.48,
        "Collection": 2364,
        "Timestamp": "2025-03-05 03:23:27"
    },
    {
        "ID": 1562425,
        "Name": "小狮子",
        "Popularity": 63673.56,
        "Collection": 116,
        "Timestamp": "2025-03-05 03:23:28"
    },
    {
        "ID": 483704,
        "Name": "小少爷的江湖",
        "Popularity": 115045.57,
        "Collection": 82,
        "Timestamp": "2025-03-05 03:23:29"
    },
    {
        "ID": 1592326,
        "Name": "荒原囚徒",
        "Popularity": 2510333.95,
        "Collection": 3955,
        "Timestamp": "2025-03-05 03:23:30"
    },
    {
        "ID": 1762950,
        "Name": "历朝年",
        "Popularity": 18475.53,
        "Collection": 15,
        "Timestamp": "2025-03-05 03:23:31"
    },
    {
        "ID": 1581652,
        "Name": "爱情复兴",
        "Popularity": 1615854.14,
        "Collection": 2887,
        "Timestamp": "2025-03-05 03:23:32"
    },
    {
        "ID": 1692606,
        "Name": "佛头青",
        "Popularity": 6387943.31,
        "Collection": 11043,
        "Timestamp": "2025-03-05 03:23:34"
    },
    {
        "ID": 1771425,
        "Name": "他在日暮之西",
        "Popularity": 178559.45,
        "Collection": 301,
        "Timestamp": "2025-03-05 03:23:36"
    },
    {
        "ID": 1712845,
        "Name": "校园歌手",
        "Popularity": 14082.52,
        "Collection": 18,
        "Timestamp": "2025-03-05 03:23:37"
    },
    {
        "ID": 1712177,
        "Name": "献我",
        "Popularity": 127629305.2,
        "Collection": 123422,
        "Timestamp": "2025-03-05 03:23:38"
    },
    {
        "ID": 1173557,
        "Name": "短篇",
        "Popularity": 1321529.48,
        "Collection": 2364,
        "Timestamp": "2025-03-05 03:23:39"
    },
    {
        "ID": 1562425,
        "Name": "小狮子",
        "Popularity": 63673.56,
        "Collection": 116,
        "Timestamp": "2025-03-05 03:23:40"
    },
    {
        "ID": 483704,
        "Name": "小少爷的江湖",
        "Popularity": 115045.57,
        "Collection": 82,
        "Timestamp": "2025-03-05 03:23:41"
    },
    {
        "ID": 1592326,
        "Name": "荒原囚徒",
        "Popularity": 2510333.95,
        "Collection": 3955,
        "Timestamp": "2025-03-05 03:23:42"
    },
    {
        "ID": 1762950,
        "Name": "历朝年",
        "Popularity": 18475.53,
        "Collection": 15,
        "Timestamp": "2025-03-05 03:23:43"
    },
    {
        "ID": 1581652,
        "Name": "爱情复兴",
        "Popularity": 1615854.14,
        "Collection": 2887,
        "Timestamp": "2025-03-05 03:23:45"
    },
    {
        "ID": 1692606,
        "Name": "佛头青",
        "Popularity": 6387943.31,
        "Collection": 11043,
        "Timestamp": "2025-03-05 03:23:45"
    },
    {
        "ID": 1819884,
        "Name": "奚别",
        "Popularity": 631.97,
        "Collection": 2,
        "Timestamp": "2025-03-05 03:23:47"
    },
    {
        "ID": 1493313,
        "Name": "不将就",
        "Popularity": 496224.16,
        "Collection": 1367,
        "Timestamp": "2025-03-05 03:23:48"
    },
    {
        "ID": 1368673,
        "Name": "君臣不相安",
        "Popularity": 8598035.23,
        "Collection": 10071,
        "Timestamp": "2025-03-05 03:23:49"
    },
    {
        "ID": 1247532,
        "Name": "说谎精与内向鬼",
        "Popularity": 45662.57,
        "Collection": 49,
        "Timestamp": "2025-03-05 03:23:50"
    },
    {
        "ID": 1665468,
        "Name": "伴青",
        "Popularity": 3224814.43,
        "Collection": 5611,
        "Timestamp": "2025-03-05 03:23:51"
    },
    {
        "ID": 1574443,
        "Name": "夜跑别在雷雨天",
        "Popularity": 17175479.81,
        "Collection": 28445,
        "Timestamp": "2025-03-05 03:23:52"
    },
    {
        "ID": 1181686,
        "Name": "踏雾来",
        "Popularity": 299281.2,
        "Collection": 1261,
        "Timestamp": "2025-03-05 03:23:53"
    },
    {
        "ID": 1292091,
        "Name": "悬鸟",
        "Popularity": 37102685.84,
        "Collection": 37710,
        "Timestamp": "2025-03-05 03:23:54"
    },
    {
        "ID": 874879,
        "Name": "冤家拍档",
        "Popularity": 790353.91,
        "Collection": 1559,
        "Timestamp": "2025-03-05 03:23:55"
    },
    {
        "ID": 1524529,
        "Name": "归潮",
        "Popularity": 795743.03,
        "Collection": 1459,
        "Timestamp": "2025-03-05 03:23:56"
    },
    {
        "ID": 720798,
        "Name": "反派当真不好当",
        "Popularity": 7648773.38,
        "Collection": 6572,
        "Timestamp": "2025-03-05 03:23:58"
    },
    {
        "ID": 1691196,
        "Name": "谋杀黄昏",
        "Popularity": 1087707.81,
        "Collection": 3614,
        "Timestamp": "2025-03-05 03:23:59"
    },
    {
        "ID": 1672755,
        "Name": "无限大学城",
        "Popularity": 689313.98,
        "Collection": 1679,
        "Timestamp": "2025-03-05 03:24:00"
    },
    {
        "ID": 1565275,
        "Name": "你看云时很近",
        "Popularity": 448036.33,
        "Collection": 1214,
        "Timestamp": "2025-03-05 03:24:01"
    },
    {
        "ID": 1460157,
        "Name": "虫族之冷漠无情的白月光",
        "Popularity": 411972.16,
        "Collection": 633,
        "Timestamp": "2025-03-05 03:24:02"
    },
    {
        "ID": 1647363,
        "Name": "暗杀对象他总撩我怎么办",
        "Popularity": 428221.35,
        "Collection": 1150,
        "Timestamp": "2025-03-05 03:24:03"
    },
    {
        "ID": 1379391,
        "Name": "触底反弹",
        "Popularity": 136557.75,
        "Collection": 345,
        "Timestamp": "2025-03-05 03:24:04"
    },
    {
        "ID": 1623062,
        "Name": "在无限游戏惨成大佬",
        "Popularity": 377680.07,
        "Collection": 811,
        "Timestamp": "2025-03-05 03:24:05"
    },
    {
        "ID": 1706695,
        "Name": "留人不住",
        "Popularity": 9446427.67,
        "Collection": 12750,
        "Timestamp": "2025-03-05 03:24:06"
    },
    {
        "ID": 1470260,
        "Name": "落星",
        "Popularity": 3305783.41,
        "Collection": 7846,
        "Timestamp": "2025-03-05 03:24:07"
    },
    {
        "ID": 1660495,
        "Name": "尘芥之境",
        "Popularity": 72967.5,
        "Collection": 104,
        "Timestamp": "2025-03-05 03:24:09"
    },
    {
        "ID": 1699123,
        "Name": "负义",
        "Popularity": 2727766.15,
        "Collection": 5512,
        "Timestamp": "2025-03-05 03:24:10"
    },
    {
        "ID": 1693166,
        "Name": "极限关系",
        "Popularity": 32871.5,
        "Collection": 69,
        "Timestamp": "2025-03-05 03:24:11"
    },
    {
        "ID": 1687556,
        "Name": "尸人说梦",
        "Popularity": 78038676.95,
        "Collection": 47492,
        "Timestamp": "2025-03-05 03:24:12"
    },
    {
        "ID": 1545303,
        "Name": "白日梦",
        "Popularity": 41589.75,
        "Collection": 242,
        "Timestamp": "2025-03-05 03:24:13"
    },
    {
        "ID": 1377840,
        "Name": "榻上臣",
        "Popularity": 232859.5,
        "Collection": 977,
        "Timestamp": "2025-03-05 03:24:14"
    },
    {
        "ID": 802128,
        "Name": "营业尴尬期",
        "Popularity": 457378.45,
        "Collection": 1699,
        "Timestamp": "2025-03-05 03:24:15"
    },
    {
        "ID": 1653015,
        "Name": "伯利恒之星",
        "Popularity": 149592.36,
        "Collection": 229,
        "Timestamp": "2025-03-05 03:24:16"
    },
    {
        "ID": 1282129,
        "Name": "亡魂飞鸟",
        "Popularity": 1692053.26,
        "Collection": 3367,
        "Timestamp": "2025-03-05 03:24:17"
    },
    {
        "ID": 1552289,
        "Name": "回南天",
        "Popularity": 424765,
        "Collection": 1880,
        "Timestamp": "2025-03-05 03:24:17"
    },
    {
        "ID": 1510047,
        "Name": "双向缺陷",
        "Popularity": 489793.75,
        "Collection": 1193,
        "Timestamp": "2025-03-05 03:24:20"
    },
    {
        "ID": 859336,
        "Name": "工号068",
        "Popularity": 9586975.39,
        "Collection": 9046,
        "Timestamp": "2025-03-05 03:24:21"
    },
    {
        "ID": 1762820,
        "Name": "失落赤道",
        "Popularity": 455194.27,
        "Collection": 1303,
        "Timestamp": "2025-03-05 03:24:22"
    },
    {
        "ID": 1806212,
        "Name": "带病穿越安全指南",
        "Popularity": 14301.8,
        "Collection": 7,
        "Timestamp": "2025-03-05 03:24:23"
    },
    {
        "ID": 1179654,
        "Name": "旺铺不招租",
        "Popularity": 7197053.34,
        "Collection": 8497,
        "Timestamp": "2025-03-05 03:24:24"
    },
    {
        "ID": 1579001,
        "Name": "剑上镖",
        "Popularity": 733807.19,
        "Collection": 1867,
        "Timestamp": "2025-03-05 03:24:25"
    },
    {
        "ID": 619707,
        "Name": "疾走千极骑",
        "Popularity": 1638837.13,
        "Collection": 3419,
        "Timestamp": "2025-03-05 03:24:25"
    },
    {
        "ID": 1443583,
        "Name": "热恋基地",
        "Popularity": 279654.57,
        "Collection": 465,
        "Timestamp": "2025-03-05 03:24:26"
    },
    {
        "ID": 1790954,
        "Name": "吗喽不想上班",
        "Popularity": 262873.03,
        "Collection": 336,
        "Timestamp": "2025-03-05 03:24:27"
    },
    {
        "ID": 1235778,
        "Name": "鹊踏枝",
        "Popularity": 865163.36,
        "Collection": 1992,
        "Timestamp": "2025-03-05 03:24:28"
    },
    {
        "ID": 1604170,
        "Name": "冰下河",
        "Popularity": 241884.1,
        "Collection": 223,
        "Timestamp": "2025-03-05 03:24:30"
    },
    {
        "ID": 1771412,
        "Name": "假想之爱",
        "Popularity": 23725.51,
        "Collection": 22,
        "Timestamp": "2025-03-05 03:24:31"
    },
    {
        "ID": 1723487,
        "Name": "以次充好",
        "Popularity": 93084.53,
        "Collection": 256,
        "Timestamp": "2025-03-05 03:24:32"
    },
    {
        "ID": 1722423,
        "Name": "问山",
        "Popularity": 134458.99,
        "Collection": 246,
        "Timestamp": "2025-03-05 03:24:33"
    },
    {
        "ID": 709509,
        "Name": "浪子",
        "Popularity": 19071652.9,
        "Collection": 19027,
        "Timestamp": "2025-03-05 03:24:34"
    },
    {
        "ID": 1530070,
        "Name": "金色柏树",
        "Popularity": 11283045.22,
        "Collection": 9851,
        "Timestamp": "2025-03-05 03:24:35"
    },
    {
        "ID": 1623835,
        "Name": "你有病吧",
        "Popularity": 580391.26,
        "Collection": 1513,
        "Timestamp": "2025-03-05 03:24:36"
    },
    {
        "ID": 1747950,
        "Name": "真爱来临的那天",
        "Popularity": 50885.04,
        "Collection": 53,
        "Timestamp": "2025-03-05 03:24:37"
    },
    {
        "ID": 1716878,
        "Name": "袭夺",
        "Popularity": 553537596.83,
        "Collection": 263928,
        "Timestamp": "2025-03-05 03:24:38"
    },
    {
        "ID": 1485147,
        "Name": "朝辞白帝",
        "Popularity": 48579.59,
        "Collection": 113,
        "Timestamp": "2025-03-05 03:24:39"
    },
    {
        "ID": 1752510,
        "Name": "止咬",
        "Popularity": 87728.58,
        "Collection": 147,
        "Timestamp": "2025-03-05 03:24:41"
    },
    {
        "ID": 1456153,
        "Name": "血太阳",
        "Popularity": 1181222.44,
        "Collection": 3361,
        "Timestamp": "2025-03-05 03:24:42"
    },
    {
        "ID": 1762732,
        "Name": "吾与万人迷孰美",
        "Popularity": 64321.36,
        "Collection": 85,
        "Timestamp": "2025-03-05 03:24:43"
    },
    {
        "ID": 1647656,
        "Name": "反派仙君归来后",
        "Popularity": 538892.47,
        "Collection": 1173,
        "Timestamp": "2025-03-05 03:24:44"
    },
    {
        "ID": 1747414,
        "Name": "枕流光",
        "Popularity": 60601.63,
        "Collection": 100,
        "Timestamp": "2025-03-05 03:24:45"
    },
    {
        "ID": 1580711,
        "Name": "隔岸观火",
        "Popularity": 107361.26,
        "Collection": 372,
        "Timestamp": "2025-03-05 03:24:45"
    },
    {
        "ID": 1150692,
        "Name": "玄乎奇迹",
        "Popularity": 96858.94,
        "Collection": 137,
        "Timestamp": "2025-03-05 03:24:46"
    },
    {
        "ID": 1586495,
        "Name": "沉柯",
        "Popularity": 5744272.74,
        "Collection": 6716,
        "Timestamp": "2025-03-05 03:24:47"
    },
    {
        "ID": 1619780,
        "Name": "欺骗游戏",
        "Popularity": 306162.97,
        "Collection": 1364,
        "Timestamp": "2025-03-05 03:24:48"
    },
    {
        "ID": 1486177,
        "Name": "挚爱错落",
        "Popularity": 990860.58,
        "Collection": 1909,
        "Timestamp": "2025-03-05 03:24:49"
    },
    {
        "ID": 1241670,
        "Name": "玫瑰茧房",
        "Popularity": 62839.56,
        "Collection": 198,
        "Timestamp": "2025-03-05 03:24:51"
    },
    {
        "ID": 1109344,
        "Name": "亲爱的穆川",
        "Popularity": 36522.87,
        "Collection": 101,
        "Timestamp": "2025-03-05 03:24:52"
    },
    {
        "ID": 1694775,
        "Name": "通感预报",
        "Popularity": 98727.35,
        "Collection": 142,
        "Timestamp": "2025-03-05 03:24:53"
    },
    {
        "ID": 1749187,
        "Name": "告白",
        "Popularity": 45239.7,
        "Collection": 164,
        "Timestamp": "2025-03-05 03:24:54"
    },
    {
        "ID": 1411759,
        "Name": "我们分手了",
        "Popularity": 786346.56,
        "Collection": 1397,
        "Timestamp": "2025-03-05 03:24:54"
    },
    {
        "ID": 1706847,
        "Name": "他怎么可能暗恋我",
        "Popularity": 6085694.47,
        "Collection": 7672,
        "Timestamp": "2025-03-05 03:24:55"
    },
    {
        "ID": 1736785,
        "Name": "金台逝水",
        "Popularity": 1021966.83,
        "Collection": 2859,
        "Timestamp": "2025-03-05 03:24:56"
    },
    {
        "ID": 1704555,
        "Name": "离婚快乐",
        "Popularity": 2702744.85,
        "Collection": 4458,
        "Timestamp": "2025-03-05 03:24:57"
    },
    {
        "ID": 1571047,
        "Name": "计青仪",
        "Popularity": 168125.79,
        "Collection": 176,
        "Timestamp": "2025-03-05 03:24:58"
    },
    {
        "ID": 1786307,
        "Name": "楔桃",
        "Popularity": 149788,
        "Collection": 386,
        "Timestamp": "2025-03-05 03:24:59"
    },
    {
        "ID": 1703392,
        "Name": "浸透翠纱",
        "Popularity": 282901.7,
        "Collection": 338,
        "Timestamp": "2025-03-05 03:25:01"
    },
    {
        "ID": 1498029,
        "Name": "不见春秋",
        "Popularity": 665092.03,
        "Collection": 1500,
        "Timestamp": "2025-03-05 03:25:02"
    },
    {
        "ID": 1695489,
        "Name": "我在恐怖游戏中一心求死",
        "Popularity": 474170.88,
        "Collection": 1272,
        "Timestamp": "2025-03-05 03:25:03"
    },
    {
        "ID": 1648461,
        "Name": "一起晒太阳",
        "Popularity": 77995.08,
        "Collection": 73,
        "Timestamp": "2025-03-05 03:25:03"
    },
    {
        "ID": 1503434,
        "Name": "跟竹马穿越到蔷薇游戏",
        "Popularity": 393167.98,
        "Collection": 796,
        "Timestamp": "2025-03-05 03:25:04"
    },
    {
        "ID": 1739413,
        "Name": "他的择偶标准是会捡破烂",
        "Popularity": 3455058.73,
        "Collection": 4212,
        "Timestamp": "2025-03-05 03:25:05"
    },
    {
        "ID": 1724886,
        "Name": "劣质真心",
        "Popularity": 4163260.47,
        "Collection": 6268,
        "Timestamp": "2025-03-05 03:25:06"
    },
    {
        "ID": 1128765,
        "Name": "虽然是爸爸的朋友但没关系",
        "Popularity": 689437.35,
        "Collection": 1568,
        "Timestamp": "2025-03-05 03:25:07"
    },
    {
        "ID": 1764738,
        "Name": "青红皂白",
        "Popularity": 154596,
        "Collection": 262,
        "Timestamp": "2025-03-05 03:25:08"
    },
    {
        "ID": 1469666,
        "Name": "下注",
        "Popularity": 68087.4,
        "Collection": 52,
        "Timestamp": "2025-03-05 03:25:09"
    },
    {
        "ID": 1762572,
        "Name": "惯性反应",
        "Popularity": 464707.72,
        "Collection": 1096,
        "Timestamp": "2025-03-05 03:25:11"
    },
    {
        "ID": 1763049,
        "Name": "铺岚",
        "Popularity": 94502.75,
        "Collection": 85,
        "Timestamp": "2025-03-05 03:25:12"
    },
    {
        "ID": 1815483,
        "Name": "良木择栖",
        "Popularity": 6908.25,
        "Collection": 6,
        "Timestamp": "2025-03-05 03:25:13"
    },
    {
        "ID": 1779294,
        "Name": "归凤阙",
        "Popularity": 57482,
        "Collection": 91,
        "Timestamp": "2025-03-05 03:25:14"
    },
    {
        "ID": 1750309,
        "Name": "明夜方可",
        "Popularity": 363554.44,
        "Collection": 631,
        "Timestamp": "2025-03-05 03:25:15"
    },
    {
        "ID": 1672640,
        "Name": "论饲养一只蛟的正确方式",
        "Popularity": 611104.75,
        "Collection": 1244,
        "Timestamp": "2025-03-05 03:25:16"
    },
    {
        "ID": 1771334,
        "Name": "切掉良心换野心",
        "Popularity": 233583.23,
        "Collection": 561,
        "Timestamp": "2025-03-05 03:25:17"
    },
    {
        "ID": 1414576,
        "Name": "六重奏",
        "Popularity": 3072287.66,
        "Collection": 5815,
        "Timestamp": "2025-03-05 03:25:18"
    },
    {
        "ID": 1803061,
        "Name": "什么我的房东竟是我的太太",
        "Popularity": 49132.75,
        "Collection": 135,
        "Timestamp": "2025-03-05 03:25:19"
    },
    {
        "ID": 1785820,
        "Name": "刺猬饲养法则",
        "Popularity": 77673.52,
        "Collection": 210,
        "Timestamp": "2025-03-05 03:25:20"
    },
    {
        "ID": 1580767,
        "Name": "千万次的见面",
        "Popularity": 3634036,
        "Collection": 4203,
        "Timestamp": "2025-03-05 03:25:21"
    },
    {
        "ID": 1373363,
        "Name": "巫山之下",
        "Popularity": 106634.5,
        "Collection": 221,
        "Timestamp": "2025-03-05 03:25:22"
    },
    {
        "ID": 1777089,
        "Name": "对五个渣攻始乱终弃后",
        "Popularity": 202281.27,
        "Collection": 248,
        "Timestamp": "2025-03-05 03:25:23"
    },
    {
        "ID": 1471221,
        "Name": "荼靡",
        "Popularity": 578776.75,
        "Collection": 2572,
        "Timestamp": "2025-03-05 03:25:24"
    },
    {
        "ID": 1773542,
        "Name": "惹眼",
        "Popularity": 163388.17,
        "Collection": 415,
        "Timestamp": "2025-03-05 03:25:25"
    },
    {
        "ID": 1592602,
        "Name": "吞声",
        "Popularity": 5329307.33,
        "Collection": 10198,
        "Timestamp": "2025-03-05 03:25:26"
    },
    {
        "ID": 1402559,
        "Name": "攻不可貌相",
        "Popularity": 25511669.03,
        "Collection": 20194,
        "Timestamp": "2025-03-05 03:25:27"
    },
    {
        "ID": 1351332,
        "Name": "彩虹连接",
        "Popularity": 2880414.74,
        "Collection": 3801,
        "Timestamp": "2025-03-05 03:25:28"
    },
    {
        "ID": 1768607,
        "Name": "十米之内",
        "Popularity": 3030109.61,
        "Collection": 7304,
        "Timestamp": "2025-03-05 03:25:29"
    },
    {
        "ID": 1792574,
        "Name": "有鬼",
        "Popularity": 15558.8,
        "Collection": 10,
        "Timestamp": "2025-03-05 03:25:29"
    },
    {
        "ID": 1174810,
        "Name": "宠物龙崽对我图谋不轨",
        "Popularity": 2735795.97,
        "Collection": 6946,
        "Timestamp": "2025-03-05 03:25:31"
    },
    {
        "ID": 827879,
        "Name": "尖塔之下",
        "Popularity": 1797773.89,
        "Collection": 5548,
        "Timestamp": "2025-03-05 03:25:32"
    },
    {
        "ID": 1715113,
        "Name": "他们都说我该死",
        "Popularity": 1651463.5,
        "Collection": 2916,
        "Timestamp": "2025-03-05 03:25:33"
    },
    {
        "ID": 1544493,
        "Name": "和死对头在游戏里结婚了",
        "Popularity": 522069.15,
        "Collection": 1105,
        "Timestamp": "2025-03-05 03:25:34"
    },
    {
        "ID": 1665113,
        "Name": "瘾欲",
        "Popularity": 8081574.01,
        "Collection": 7745,
        "Timestamp": "2025-03-05 03:25:35"
    },
    {
        "ID": 307507,
        "Name": "双徐记",
        "Popularity": 7160.59,
        "Collection": 12,
        "Timestamp": "2025-03-05 03:25:36"
    },
    {
        "ID": 969721,
        "Name": "恋爱脑他重生了",
        "Popularity": 12514207.09,
        "Collection": 8944,
        "Timestamp": "2025-03-05 03:25:37"
    },
    {
        "ID": 1755248,
        "Name": "禁锢日出",
        "Popularity": 196184,
        "Collection": 473,
        "Timestamp": "2025-03-05 03:25:37"
    },
    {
        "ID": 1747587,
        "Name": "永恒月光",
        "Popularity": 192633.75,
        "Collection": 179,
        "Timestamp": "2025-03-05 03:25:38"
    },
    {
        "ID": 1691939,
        "Name": "渡灵",
        "Popularity": 60636.62,
        "Collection": 69,
        "Timestamp": "2025-03-05 03:25:39"
    },
    {
        "ID": 1640384,
        "Name": "和死对头一起穿到了ABO",
        "Popularity": 2262744.49,
        "Collection": 5179,
        "Timestamp": "2025-03-05 03:25:41"
    },
    {
        "ID": 1637579,
        "Name": "孤棹",
        "Popularity": 288493.25,
        "Collection": 429,
        "Timestamp": "2025-03-05 03:25:42"
    },
    {
        "ID": 1376216,
        "Name": "睡后吻",
        "Popularity": 744675.25,
        "Collection": 3711,
        "Timestamp": "2025-03-05 03:25:43"
    },
    {
        "ID": 1234980,
        "Name": "欺君",
        "Popularity": 15978381.41,
        "Collection": 19864,
        "Timestamp": "2025-03-05 03:25:44"
    },
    {
        "ID": 1212455,
        "Name": "替嫁之将",
        "Popularity": 41487225.75,
        "Collection": 21086,
        "Timestamp": "2025-03-05 03:25:45"
    },
    {
        "ID": 311953,
        "Name": "早去早回",
        "Popularity": 2711657.31,
        "Collection": 3639,
        "Timestamp": "2025-03-05 03:25:46"
    },
    {
        "ID": 1548723,
        "Name": "肮脏之地",
        "Popularity": 5030944.79,
        "Collection": 6456,
        "Timestamp": "2025-03-05 03:25:47"
    },
    {
        "ID": 1639754,
        "Name": "野色蔓延",
        "Popularity": 538853.95,
        "Collection": 1029,
        "Timestamp": "2025-03-05 03:25:47"
    },
    {
        "ID": 1309776,
        "Name": "刻板印象",
        "Popularity": 30396.64,
        "Collection": 69,
        "Timestamp": "2025-03-05 03:25:48"
    },
    {
        "ID": 1820032,
        "Name": "无限推理",
        "Popularity": 276.96,
        "Collection": 1,
        "Timestamp": "2025-03-05 03:25:49"
    },
    {
        "ID": 1274556,
        "Name": "两人三恋",
        "Popularity": 364143.65,
        "Collection": 1867,
        "Timestamp": "2025-03-05 03:25:51"
    },
    {
        "ID": 1736761,
        "Name": "不见万物",
        "Popularity": 284749.5,
        "Collection": 394,
        "Timestamp": "2025-03-05 03:25:52"
    },
    {
        "ID": 1667764,
        "Name": "冷幻觉",
        "Popularity": 27823067.17,
        "Collection": 26653,
        "Timestamp": "2025-03-05 03:25:53"
    },
    {
        "ID": 1654840,
        "Name": "阮阮",
        "Popularity": 614572.35,
        "Collection": 1787,
        "Timestamp": "2025-03-05 03:25:54"
    },
    {
        "ID": 1640519,
        "Name": "谒金门",
        "Popularity": 6529703.18,
        "Collection": 8031,
        "Timestamp": "2025-03-05 03:25:55"
    },
    {
        "ID": 1747881,
        "Name": "直到他想杀死我",
        "Popularity": 1254300.38,
        "Collection": 4532,
        "Timestamp": "2025-03-05 03:25:56"
    },
    {
        "ID": 1710145,
        "Name": "空降男团后",
        "Popularity": 1508030,
        "Collection": 3956,
        "Timestamp": "2025-03-05 03:25:57"
    },
    {
        "ID": 1653254,
        "Name": "徽影重重",
        "Popularity": 94635.5,
        "Collection": 111,
        "Timestamp": "2025-03-05 03:25:58"
    },
    {
        "ID": 1346127,
        "Name": "王者",
        "Popularity": 628117.5,
        "Collection": 1688,
        "Timestamp": "2025-03-05 03:25:58"
    },
    {
        "ID": 1543878,
        "Name": "上错坟",
        "Popularity": 214267.16,
        "Collection": 522,
        "Timestamp": "2025-03-05 03:25:59"
    },
    {
        "ID": 1774807,
        "Name": "点痣",
        "Popularity": 144478.5,
        "Collection": 124,
        "Timestamp": "2025-03-05 03:26:01"
    },
    {
        "ID": 1554296,
        "Name": "全能悖论",
        "Popularity": 3975100.34,
        "Collection": 8232,
        "Timestamp": "2025-03-05 03:26:02"
    },
    {
        "ID": 1816179,
        "Name": "金苹果弥撒",
        "Popularity": 9482.85,
        "Collection": 10,
        "Timestamp": "2025-03-05 03:26:03"
    },
    {
        "ID": 1807261,
        "Name": "天灯燃尽",
        "Popularity": 3658.25,
        "Collection": 1,
        "Timestamp": "2025-03-05 03:26:04"
    },
    {
        "ID": 1805238,
        "Name": "小月亮",
        "Popularity": 436536.56,
        "Collection": 1088,
        "Timestamp": "2025-03-05 03:26:05"
    },
    {
        "ID": 1805203,
        "Name": "真爱价码",
        "Popularity": 35564.25,
        "Collection": 58,
        "Timestamp": "2025-03-05 03:26:06"
    },
    {
        "ID": 1768791,
        "Name": "病院",
        "Popularity": 28580,
        "Collection": 117,
        "Timestamp": "2025-03-05 03:26:07"
    },
    {
        "ID": 1755823,
        "Name": "我带钥匙有用吗",
        "Popularity": 20074905.33,
        "Collection": 17609,
        "Timestamp": "2025-03-05 03:26:08"
    },
    {
        "ID": 1748361,
        "Name": "认识你我愿赌服输",
        "Popularity": 21229.75,
        "Collection": 4,
        "Timestamp": "2025-03-05 03:26:08"
    },
    {
        "ID": 1627315,
        "Name": "我爱你是在今天",
        "Popularity": 677746,
        "Collection": 1338,
        "Timestamp": "2025-03-05 03:26:09"
    },
    {
        "ID": 1619249,
        "Name": "大野",
        "Popularity": 56077.25,
        "Collection": 117,
        "Timestamp": "2025-03-05 03:26:11"
    },
    {
        "ID": 1584483,
        "Name": "绝命胶片",
        "Popularity": 972497.25,
        "Collection": 1801,
        "Timestamp": "2025-03-05 03:26:12"
    },
    {
        "ID": 1526569,
        "Name": "金瓯重圆",
        "Popularity": 4052570.2,
        "Collection": 4046,
        "Timestamp": "2025-03-05 03:26:13"
    },
    {
        "ID": 1357283,
        "Name": "夺缘",
        "Popularity": 158601.25,
        "Collection": 220,
        "Timestamp": "2025-03-05 03:26:14"
    },
    {
        "ID": 207295,
        "Name": "王妃每天都想和离",
        "Popularity": 164229,
        "Collection": 363,
        "Timestamp": "2025-03-05 03:26:15"
    },
    {
        "ID": 1818258,
        "Name": "愈禾日志",
        "Popularity": 3121.47,
        "Collection": 13,
        "Timestamp": "2025-03-05 03:26:16"
    },
    {
        "ID": 1644105,
        "Name": "又逢江南",
        "Popularity": 295201.6,
        "Collection": 501,
        "Timestamp": "2025-03-05 03:26:16"
    },
    {
        "ID": 1488525,
        "Name": "长仙",
        "Popularity": 177395.25,
        "Collection": 377,
        "Timestamp": "2025-03-05 03:26:17"
    },
    {
        "ID": 1785221,
        "Name": "贪得无厌",
        "Popularity": 12109.43,
        "Collection": 12,
        "Timestamp": "2025-03-05 03:26:18"
    },
    {
        "ID": 345712,
        "Name": "至死不渝",
        "Popularity": 219379357.81,
        "Collection": 90520,
        "Timestamp": "2025-03-05 03:26:19"
    },
    {
        "ID": 1683831,
        "Name": "孩子气",
        "Popularity": 298855,
        "Collection": 683,
        "Timestamp": "2025-03-05 03:26:21"
    },
    {
        "ID": 1798130,
        "Name": "失效安全词",
        "Popularity": 21784.95,
        "Collection": 27,
        "Timestamp": "2025-03-05 03:26:22"
    },
    {
        "ID": 1771438,
        "Name": "时泅",
        "Popularity": 53620.07,
        "Collection": 42,
        "Timestamp": "2025-03-05 03:26:23"
    },
    {
        "ID": 1759319,
        "Name": "都有病",
        "Popularity": 661102.06,
        "Collection": 1023,
        "Timestamp": "2025-03-05 03:26:24"
    },
    {
        "ID": 1744815,
        "Name": "春日以北",
        "Popularity": 204200.25,
        "Collection": 394,
        "Timestamp": "2025-03-05 03:26:24"
    },
    {
        "ID": 1727217,
        "Name": "如果今夜不下雨",
        "Popularity": 6318143.2,
        "Collection": 7357,
        "Timestamp": "2025-03-05 03:26:25"
    },
    {
        "ID": 1592390,
        "Name": "吴医生，干脆这样",
        "Popularity": 226513.98,
        "Collection": 565,
        "Timestamp": "2025-03-05 03:26:26"
    },
    {
        "ID": 1584377,
        "Name": "温柔的利用金手指的方法",
        "Popularity": 1002925.92,
        "Collection": 1798,
        "Timestamp": "2025-03-05 03:26:27"
    },
    {
        "ID": 1520908,
        "Name": "浮光",
        "Popularity": 464064,
        "Collection": 831,
        "Timestamp": "2025-03-05 03:26:28"
    },
    {
        "ID": 1352214,
        "Name": "欺欺暧暧",
        "Popularity": 6691.5,
        "Collection": 10,
        "Timestamp": "2025-03-05 03:26:29"
    },
    {
        "ID": 257085,
        "Name": "NPC攻略准则",
        "Popularity": 67518.47,
        "Collection": 350,
        "Timestamp": "2025-03-05 03:26:31"
    },
    {
        "ID": 1780297,
        "Name": "病态循环",
        "Popularity": 124370.99,
        "Collection": 270,
        "Timestamp": "2025-03-05 03:26:32"
    },
    {
        "ID": 1743725,
        "Name": "拯救恋爱脑计划",
        "Popularity": 124080.18,
        "Collection": 262,
        "Timestamp": "2025-03-05 03:26:33"
    },
    {
        "ID": 1659167,
        "Name": "无根之罪",
        "Popularity": 193489.35,
        "Collection": 833,
        "Timestamp": "2025-03-05 03:26:34"
    },
    {
        "ID": 1755760,
        "Name": "焉知",
        "Popularity": 351383.69,
        "Collection": 852,
        "Timestamp": "2025-03-05 03:26:35"
    },
    {
        "ID": 1801257,
        "Name": "衔青",
        "Popularity": 17231,
        "Collection": 6,
        "Timestamp": "2025-03-05 03:26:35"
    },
    {
        "ID": 1782012,
        "Name": "牵线飞鸟",
        "Popularity": 65681.75,
        "Collection": 119,
        "Timestamp": "2025-03-05 03:26:36"
    },
    {
        "ID": 1786615,
        "Name": "永夜调",
        "Popularity": 39825.91,
        "Collection": 7,
        "Timestamp": "2025-03-05 03:26:37"
    },
    {
        "ID": 742172,
        "Name": "定风波",
        "Popularity": 218707.48,
        "Collection": 290,
        "Timestamp": "2025-03-05 03:26:38"
    },
    {
        "ID": 1646891,
        "Name": "休想",
        "Popularity": 6456135.31,
        "Collection": 10563,
        "Timestamp": "2025-03-05 03:26:39"
    },
    {
        "ID": 1804722,
        "Name": "臣服斯文",
        "Popularity": 211994.31,
        "Collection": 616,
        "Timestamp": "2025-03-05 03:26:41"
    },
    {
        "ID": 1744374,
        "Name": "野心勃勃",
        "Popularity": 154168.75,
        "Collection": 324,
        "Timestamp": "2025-03-05 03:26:42"
    },
    {
        "ID": 1807614,
        "Name": "逆转明日梦",
        "Popularity": 5428765,
        "Collection": 10479,
        "Timestamp": "2025-03-05 03:26:43"
    },
    {
        "ID": 1805481,
        "Name": "蝴蝶坠地",
        "Popularity": 19269.5,
        "Collection": 28,
        "Timestamp": "2025-03-05 03:26:44"
    },
    {
        "ID": 1748353,
        "Name": "兜圈",
        "Popularity": 217514,
        "Collection": 276,
        "Timestamp": "2025-03-05 03:26:45"
    },
    {
        "ID": 1637585,
        "Name": "庶子生存法则",
        "Popularity": 2455494.42,
        "Collection": 4833,
        "Timestamp": "2025-03-05 03:26:46"
    },
    {
        "ID": 1579289,
        "Name": "缺觉",
        "Popularity": 7526245.25,
        "Collection": 11420,
        "Timestamp": "2025-03-05 03:26:46"
    },
    {
        "ID": 1475757,
        "Name": "不要吸我啦！",
        "Popularity": 1646232.02,
        "Collection": 4201,
        "Timestamp": "2025-03-05 03:26:47"
    },
    {
        "ID": 1712415,
        "Name": "许老师移情实录",
        "Popularity": 139604.34,
        "Collection": 239,
        "Timestamp": "2025-03-05 03:26:48"
    },
    {
        "ID": 1614828,
        "Name": "山风折水",
        "Popularity": 495703.06,
        "Collection": 877,
        "Timestamp": "2025-03-05 03:26:49"
    },
    {
        "ID": 1766993,
        "Name": "接吻三分钟",
        "Popularity": 308321.25,
        "Collection": 1227,
        "Timestamp": "2025-03-05 03:26:51"
    },
    {
        "ID": 1753133,
        "Name": "上位者沉沦",
        "Popularity": 185260.85,
        "Collection": 304,
        "Timestamp": "2025-03-05 03:26:52"
    },
    {
        "ID": 1416779,
        "Name": "殿下为我两肋插刀",
        "Popularity": 259926.75,
        "Collection": 512,
        "Timestamp": "2025-03-05 03:26:53"
    },
    {
        "ID": 1745415,
        "Name": "妄念",
        "Popularity": 120301.53,
        "Collection": 125,
        "Timestamp": "2025-03-05 03:26:54"
    },
    {
        "ID": 1569146,
        "Name": "落日之下",
        "Popularity": 149007.52,
        "Collection": 352,
        "Timestamp": "2025-03-05 03:26:55"
    },
    {
        "ID": 117268,
        "Name": "尘霜微凉",
        "Popularity": 74174205.41,
        "Collection": 26470,
        "Timestamp": "2025-03-05 03:26:56"
    },
    {
        "ID": 1658382,
        "Name": "我有一台挖掘机",
        "Popularity": 692892.14,
        "Collection": 927,
        "Timestamp": "2025-03-05 03:26:56"
    },
    {
        "ID": 1790802,
        "Name": "六个便士与月亮",
        "Popularity": 2807.76,
        "Collection": 1,
        "Timestamp": "2025-03-05 03:26:57"
    },
    {
        "ID": 1591490,
        "Name": "万竞霜不想干了",
        "Popularity": 1023082.77,
        "Collection": 2875,
        "Timestamp": "2025-03-05 03:26:58"
    },
    {
        "ID": 1144360,
        "Name": "日落收藏家",
        "Popularity": 2191221.95,
        "Collection": 8506,
        "Timestamp": "2025-03-05 03:26:59"
    },
    {
        "ID": 1635285,
        "Name": "失明症",
        "Popularity": 56856.43,
        "Collection": 74,
        "Timestamp": "2025-03-05 03:27:01"
    },
    {
        "ID": 1797539,
        "Name": "今夜有雪",
        "Popularity": 4082.38,
        "Collection": 3,
        "Timestamp": "2025-03-05 03:27:02"
    },
    {
        "ID": 1761932,
        "Name": "铃兰骑士",
        "Popularity": 17774.15,
        "Collection": 11,
        "Timestamp": "2025-03-05 03:27:03"
    },
    {
        "ID": 1819403,
        "Name": "热带飞行",
        "Popularity": 757.93,
        "Collection": 3,
        "Timestamp": "2025-03-05 03:27:04"
    },
    {
        "ID": 1699668,
        "Name": "stop！停止发癫",
        "Popularity": 1773940.53,
        "Collection": 5861,
        "Timestamp": "2025-03-05 03:27:05"
    },
    {
        "ID": 1736357,
        "Name": "别在难堪时伸手",
        "Popularity": 268872.1,
        "Collection": 724,
        "Timestamp": "2025-03-05 03:27:06"
    },
    {
        "ID": 1379278,
        "Name": "双面人生",
        "Popularity": 628063.91,
        "Collection": 1705,
        "Timestamp": "2025-03-05 03:27:07"
    },
    {
        "ID": 1797436,
        "Name": "昨日沉湎",
        "Popularity": 123880.06,
        "Collection": 37,
        "Timestamp": "2025-03-05 03:27:07"
    },
    {
        "ID": 1819621,
        "Name": "里斯秦庄",
        "Popularity": 1519.65,
        "Collection": 5,
        "Timestamp": "2025-03-05 03:27:08"
    },
    {
        "ID": 1592626,
        "Name": "破格",
        "Popularity": 716847.67,
        "Collection": 1053,
        "Timestamp": "2025-03-05 03:27:09"
    },
    {
        "ID": 1435610,
        "Name": " 玩物",
        "Popularity": 257500.27,
        "Collection": 1564,
        "Timestamp": "2025-03-05 03:27:11"
    },
    {
        "ID": 1805245,
        "Name": "妄恋共感",
        "Popularity": 15088.92,
        "Collection": 45,
        "Timestamp": "2025-03-05 03:27:12"
    },
    {
        "ID": 1769046,
        "Name": "杀死那支华尔兹",
        "Popularity": 79918.25,
        "Collection": 167,
        "Timestamp": "2025-03-05 03:27:13"
    },
    {
        "ID": 1713824,
        "Name": "杀死那个beta卧底",
        "Popularity": 24310.59,
        "Collection": 64,
        "Timestamp": "2025-03-05 03:27:14"
    },
    {
        "ID": 1806238,
        "Name": "东风恶",
        "Popularity": 15475.75,
        "Collection": 12,
        "Timestamp": "2025-03-05 03:27:15"
    },
    {
        "ID": 1720205,
        "Name": "美强惨男主拯救指南",
        "Popularity": 1098028.28,
        "Collection": 2586,
        "Timestamp": "2025-03-05 03:27:15"
    },
    {
        "ID": 1615817,
        "Name": "游人指南",
        "Popularity": 74842.76,
        "Collection": 115,
        "Timestamp": "2025-03-05 03:27:16"
    },
    {
        "ID": 1751484,
        "Name": "残鸣不响",
        "Popularity": 368970.92,
        "Collection": 868,
        "Timestamp": "2025-03-05 03:27:17"
    },
    {
        "ID": 1689773,
        "Name": "长日飞光",
        "Popularity": 146775.25,
        "Collection": 143,
        "Timestamp": "2025-03-05 03:27:18"
    },
    {
        "ID": 1815510,
        "Name": "反派魔尊穿成师尊受后",
        "Popularity": 8468.5,
        "Collection": 16,
        "Timestamp": "2025-03-05 03:27:19"
    },
    {
        "ID": 1809475,
        "Name": "错位",
        "Popularity": 16157.25,
        "Collection": 46,
        "Timestamp": "2025-03-05 03:27:21"
    },
    {
        "ID": 1800100,
        "Name": "蝴蝶眨几次眼睛",
        "Popularity": 563291.5,
        "Collection": 1746,
        "Timestamp": "2025-03-05 03:27:22"
    },
    {
        "ID": 1799091,
        "Name": "我醉欲眠",
        "Popularity": 32512.18,
        "Collection": 23,
        "Timestamp": "2025-03-05 03:27:23"
    },
    {
        "ID": 1791477,
        "Name": "特聘道侣",
        "Popularity": 3653,
        "Collection": 2,
        "Timestamp": "2025-03-05 03:27:24"
    },
    {
        "ID": 1782959,
        "Name": "捕君心",
        "Popularity": 117927,
        "Collection": 218,
        "Timestamp": "2025-03-05 03:27:24"
    },
    {
        "ID": 1781311,
        "Name": "坠落返生",
        "Popularity": 11482.83,
        "Collection": 19,
        "Timestamp": "2025-03-05 03:27:25"
    },
    {
        "ID": 1776695,
        "Name": "声声",
        "Popularity": 25847.25,
        "Collection": 21,
        "Timestamp": "2025-03-05 03:27:26"
    },
    {
        "ID": 1750204,
        "Name": "真实遗愿清单",
        "Popularity": 11144008,
        "Collection": 39728,
        "Timestamp": "2025-03-05 03:27:27"
    },
    {
        "ID": 1732769,
        "Name": "劫神",
        "Popularity": 1310671.5,
        "Collection": 1458,
        "Timestamp": "2025-03-05 03:27:28"
    },
    {
        "ID": 1732219,
        "Name": "百雀煞",
        "Popularity": 288401.5,
        "Collection": 238,
        "Timestamp": "2025-03-05 03:27:29"
    },
    {
        "ID": 1706518,
        "Name": "给我抄抄",
        "Popularity": 513770.29,
        "Collection": 1917,
        "Timestamp": "2025-03-05 03:27:31"
    },
    {
        "ID": 1698771,
        "Name": "银行狗的春天",
        "Popularity": 599262.78,
        "Collection": 1105,
        "Timestamp": "2025-03-05 03:27:32"
    },
    {
        "ID": 1599931,
        "Name": "狂宴",
        "Popularity": 82020.25,
        "Collection": 28,
        "Timestamp": "2025-03-05 03:27:32"
    },
    {
        "ID": 1553244,
        "Name": "见春天树",
        "Popularity": 489445,
        "Collection": 1116,
        "Timestamp": "2025-03-05 03:27:33"
    },
    {
        "ID": 1506220,
        "Name": "兔比特",
        "Popularity": 7446031.25,
        "Collection": 8638,
        "Timestamp": "2025-03-05 03:27:34"
    },
    {
        "ID": 1401463,
        "Name": "离婚冷静期",
        "Popularity": 714750.87,
        "Collection": 3918,
        "Timestamp": "2025-03-05 03:27:35"
    },
    {
        "ID": 1777278,
        "Name": "致命鱿物",
        "Popularity": 3049403.82,
        "Collection": 4080,
        "Timestamp": "2025-03-05 03:27:36"
    },
    {
        "ID": 853557,
        "Name": "荔枝角曼波",
        "Popularity": 5791727.27,
        "Collection": 9875,
        "Timestamp": "2025-03-05 03:27:37"
    },
    {
        "ID": 1715187,
        "Name": "怎么会有神棍怕鬼啊",
        "Popularity": 305791.97,
        "Collection": 759,
        "Timestamp": "2025-03-05 03:27:38"
    },
    {
        "ID": 1775802,
        "Name": "坍塌太阳",
        "Popularity": 29114.21,
        "Collection": 12,
        "Timestamp": "2025-03-05 03:27:39"
    },
    {
        "ID": 1401787,
        "Name": "猎神游戏",
        "Popularity": 290773.69,
        "Collection": 632,
        "Timestamp": "2025-03-05 03:27:41"
    },
    {
        "ID": 647886,
        "Name": "规则是禁止私联",
        "Popularity": 565646.75,
        "Collection": 2056,
        "Timestamp": "2025-03-05 03:27:42"
    },
    {
        "ID": 1745907,
        "Name": "我是直男来着",
        "Popularity": 242428.57,
        "Collection": 595,
        "Timestamp": "2025-03-05 03:27:43"
    },
    {
        "ID": 1785658,
        "Name": "雨后闻腥",
        "Popularity": 9538390.93,
        "Collection": 25523,
        "Timestamp": "2025-03-05 03:27:44"
    },
    {
        "ID": 1499589,
        "Name": "候鸟与翠榴石",
        "Popularity": 10920958.9,
        "Collection": 9125,
        "Timestamp": "2025-03-05 03:27:44"
    },
    {
        "ID": 1414867,
        "Name": "假面之罪",
        "Popularity": 8450840.62,
        "Collection": 9198,
        "Timestamp": "2025-03-05 03:27:45"
    },
    {
        "ID": 1368713,
        "Name": "队长，让我吸一口",
        "Popularity": 55830.54,
        "Collection": 320,
        "Timestamp": "2025-03-05 03:27:46"
    },
    {
        "ID": 1707256,
        "Name": "笑话",
        "Popularity": 236059.75,
        "Collection": 779,
        "Timestamp": "2025-03-05 03:27:47"
    },
    {
        "ID": 1451042,
        "Name": "偏倚",
        "Popularity": 26299.25,
        "Collection": 32,
        "Timestamp": "2025-03-05 03:27:48"
    },
    {
        "ID": 1728883,
        "Name": "和死对头网恋后翻车了",
        "Popularity": 718316.32,
        "Collection": 2049,
        "Timestamp": "2025-03-05 03:27:49"
    },
    {
        "ID": 1798488,
        "Name": "山风遇惊鸟",
        "Popularity": 28589.5,
        "Collection": 14,
        "Timestamp": "2025-03-05 03:27:51"
    },
    {
        "ID": 1748589,
        "Name": "稳赔不赚",
        "Popularity": 915595.78,
        "Collection": 1315,
        "Timestamp": "2025-03-05 03:27:52"
    },
    {
        "ID": 1732789,
        "Name": "散尽残阳",
        "Popularity": 361228.25,
        "Collection": 894,
        "Timestamp": "2025-03-05 03:27:53"
    },
    {
        "ID": 1363216,
        "Name": "暗恋对象他非要跟我结婚",
        "Popularity": 51359,
        "Collection": 138,
        "Timestamp": "2025-03-05 03:27:54"
    },
    {
        "ID": 1615367,
        "Name": "到底是谁在觊觎我！",
        "Popularity": 229246.36,
        "Collection": 225,
        "Timestamp": "2025-03-05 03:27:55"
    },
    {
        "ID": 1807829,
        "Name": "ISO感光度",
        "Popularity": 12487.77,
        "Collection": 8,
        "Timestamp": "2025-03-05 03:27:56"
    },
    {
        "ID": 1800757,
        "Name": "楚楚可为",
        "Popularity": 14254.79,
        "Collection": 5,
        "Timestamp": "2025-03-05 03:27:57"
    },
    {
        "ID": 1764589,
        "Name": "春风对",
        "Popularity": 39085.5,
        "Collection": 36,
        "Timestamp": "2025-03-05 03:27:57"
    },
    {
        "ID": 1558200,
        "Name": "扰我清梦",
        "Popularity": 78244.54,
        "Collection": 4,
        "Timestamp": "2025-03-05 03:27:58"
    },
    {
        "ID": 1815649,
        "Name": "淬火效应",
        "Popularity": 4964.25,
        "Collection": 3,
        "Timestamp": "2025-03-05 03:27:59"
    },
    {
        "ID": 1760441,
        "Name": "爱有时差",
        "Popularity": 50549.25,
        "Collection": 53,
        "Timestamp": "2025-03-05 03:28:01"
    },
    {
        "ID": 1752263,
        "Name": "汪汪队立大功",
        "Popularity": 15719.52,
        "Collection": 29,
        "Timestamp": "2025-03-05 03:28:02"
    },
    {
        "ID": 1735930,
        "Name": "岁月知长夏",
        "Popularity": 802181,
        "Collection": 1526,
        "Timestamp": "2025-03-05 03:28:03"
    },
    {
        "ID": 1683594,
        "Name": "禁止天真",
        "Popularity": 7612251.41,
        "Collection": 9536,
        "Timestamp": "2025-03-05 03:28:04"
    },
    {
        "ID": 1768258,
        "Name": "空洞爱情",
        "Popularity": 938855.2,
        "Collection": 2177,
        "Timestamp": "2025-03-05 03:28:05"
    },
    {
        "ID": 1816301,
        "Name": "午夜爱人",
        "Popularity": 6247.01,
        "Collection": 4,
        "Timestamp": "2025-03-05 03:28:05"
    },
    {
        "ID": 1578920,
        "Name": "卤水点豆腐",
        "Popularity": 11275147.07,
        "Collection": 15179,
        "Timestamp": "2025-03-05 03:28:06"
    },
    {
        "ID": 1170470,
        "Name": "缚春恩",
        "Popularity": 11475821.4,
        "Collection": 15433,
        "Timestamp": "2025-03-05 03:28:07"
    },
    {
        "ID": 1812560,
        "Name": "IDUN漪瞳",
        "Popularity": 4525.25,
        "Collection": 10,
        "Timestamp": "2025-03-05 03:28:08"
    },
    {
        "ID": 1642838,
        "Name": "汹涌",
        "Popularity": 392760.56,
        "Collection": 1074,
        "Timestamp": "2025-03-05 03:28:09"
    },
    {
        "ID": 1761060,
        "Name": "师弟不知道",
        "Popularity": 731285.58,
        "Collection": 1632,
        "Timestamp": "2025-03-05 03:28:11"
    },
    {
        "ID": 1751111,
        "Name": "寻妖",
        "Popularity": 48182.25,
        "Collection": 51,
        "Timestamp": "2025-03-05 03:28:12"
    },
    {
        "ID": 1725415,
        "Name": "童养夫",
        "Popularity": 404567.5,
        "Collection": 1277,
        "Timestamp": "2025-03-05 03:28:13"
    },
    {
        "ID": 1719913,
        "Name": "高校教师生存日记",
        "Popularity": 2652110.25,
        "Collection": 10704,
        "Timestamp": "2025-03-05 03:28:13"
    },
    {
        "ID": 1816500,
        "Name": "之死靡他",
        "Popularity": 6673.2,
        "Collection": 0,
        "Timestamp": "2025-03-05 03:28:14"
    },
    {
        "ID": 1766011,
        "Name": "他的献吻",
        "Popularity": 35628.08,
        "Collection": 33,
        "Timestamp": "2025-03-05 03:28:15"
    },
    {
        "ID": 1760325,
        "Name": "把系统噶了怎么办",
        "Popularity": 55540.25,
        "Collection": 26,
        "Timestamp": "2025-03-05 03:28:16"
    },
    {
        "ID": 1326238,
        "Name": "星火不息",
        "Popularity": 5881956.99,
        "Collection": 10220,
        "Timestamp": "2025-03-05 03:28:17"
    },
    {
        "ID": 1767547,
        "Name": "养嗔为患",
        "Popularity": 53679.02,
        "Collection": 47,
        "Timestamp": "2025-03-05 03:28:18"
    },
    {
        "ID": 1735105,
        "Name": "天岛效应",
        "Popularity": 48451588.98,
        "Collection": 55095,
        "Timestamp": "2025-03-05 03:28:19"
    },
    {
        "ID": 1752024,
        "Name": "风月薄幸",
        "Popularity": 223495.5,
        "Collection": 542,
        "Timestamp": "2025-03-05 03:28:21"
    },
    {
        "ID": 1616587,
        "Name": "鸣天的礼物",
        "Popularity": 524731.52,
        "Collection": 1077,
        "Timestamp": "2025-03-05 03:28:21"
    },
    {
        "ID": 1732956,
        "Name": "尾冬",
        "Popularity": 109064.9,
        "Collection": 71,
        "Timestamp": "2025-03-05 03:28:22"
    },
    {
        "ID": 1613747,
        "Name": "烂桃子",
        "Popularity": 298041.33,
        "Collection": 841,
        "Timestamp": "2025-03-05 03:28:23"
    },
    {
        "ID": 1388451,
        "Name": "君莫道",
        "Popularity": 1747857.34,
        "Collection": 3287,
        "Timestamp": "2025-03-05 03:28:24"
    },
    {
        "ID": 1416499,
        "Name": "心软",
        "Popularity": 7734694.42,
        "Collection": 9110,
        "Timestamp": "2025-03-05 03:28:25"
    },
    {
        "ID": 1638374,
        "Name": "渣受今天也想提分手",
        "Popularity": 1022073.14,
        "Collection": 1042,
        "Timestamp": "2025-03-05 03:28:26"
    },
    {
        "ID": 1694869,
        "Name": "海上共潮生",
        "Popularity": 18642415.01,
        "Collection": 12075,
        "Timestamp": "2025-03-05 03:28:27"
    },
    {
        "ID": 1785482,
        "Name": "魔尊不让我当咸鱼",
        "Popularity": 21535.7,
        "Collection": 16,
        "Timestamp": "2025-03-05 03:28:28"
    },
    {
        "ID": 1652843,
        "Name": "不期",
        "Popularity": 3000304.35,
        "Collection": 2814,
        "Timestamp": "2025-03-05 03:28:29"
    },
    {
        "ID": 1509532,
        "Name": "天意浮沉",
        "Popularity": 914471.63,
        "Collection": 1534,
        "Timestamp": "2025-03-05 03:28:31"
    },
    {
        "ID": 1768195,
        "Name": "惊梦",
        "Popularity": 126246.24,
        "Collection": 130,
        "Timestamp": "2025-03-05 03:28:31"
    },
    {
        "ID": 1751140,
        "Name": "春天见",
        "Popularity": 4078197.76,
        "Collection": 5622,
        "Timestamp": "2025-03-05 03:28:32"
    },
    {
        "ID": 1592883,
        "Name": "神山上的宗宗格纳",
        "Popularity": 47908.94,
        "Collection": 74,
        "Timestamp": "2025-03-05 03:28:33"
    },
    {
        "ID": 1801788,
        "Name": "刻舟爱河上",
        "Popularity": 118499.97,
        "Collection": 266,
        "Timestamp": "2025-03-05 03:28:34"
    },
    {
        "ID": 1649448,
        "Name": "破坏欲",
        "Popularity": 1445345.29,
        "Collection": 4232,
        "Timestamp": "2025-03-05 03:28:35"
    },
    {
        "ID": 1801929,
        "Name": "潮汐",
        "Popularity": 94978.61,
        "Collection": 81,
        "Timestamp": "2025-03-05 03:28:36"
    },
    {
        "ID": 1590155,
        "Name": "言不由衷",
        "Popularity": 1354435.74,
        "Collection": 3465,
        "Timestamp": "2025-03-05 03:28:37"
    },
    {
        "ID": 1814876,
        "Name": "做一只猫",
        "Popularity": 16.22,
        "Collection": 0,
        "Timestamp": "2025-03-05 03:28:38"
    },
    {
        "ID": 1775407,
        "Name": "回旋",
        "Popularity": 657027.03,
        "Collection": 1721,
        "Timestamp": "2025-03-05 03:28:39"
    },
    {
        "ID": 1811179,
        "Name": "他难追",
        "Popularity": 11348,
        "Collection": 14,
        "Timestamp": "2025-03-05 03:28:41"
    },
    {
        "ID": 1328781,
        "Name": "执笔落你",
        "Popularity": 138737.9,
        "Collection": 373,
        "Timestamp": "2025-03-05 03:28:42"
    },
    {
        "ID": 1740528,
        "Name": "错误治疗指南",
        "Popularity": 118165.91,
        "Collection": 248,
        "Timestamp": "2025-03-05 03:28:43"
    },
    {
        "ID": 1426641,
        "Name": "恋爱序言",
        "Popularity": 7633747.73,
        "Collection": 12588,
        "Timestamp": "2025-03-05 03:28:44"
    },
    {
        "ID": 1488111,
        "Name": "听说全世界都要拆散我们",
        "Popularity": 114576.96,
        "Collection": 194,
        "Timestamp": "2025-03-05 03:28:44"
    },
    {
        "ID": 1814737,
        "Name": "1992摇滚与上学live",
        "Popularity": 670938.24,
        "Collection": 337,
        "Timestamp": "2025-03-05 03:28:46"
    },
    {
        "ID": 1731402,
        "Name": "隐燃",
        "Popularity": 4648301.18,
        "Collection": 5896,
        "Timestamp": "2025-03-05 03:28:46"
    },
    {
        "ID": 1782608,
        "Name": "伪人收容所",
        "Popularity": 34965.52,
        "Collection": 36,
        "Timestamp": "2025-03-05 03:28:47"
    },
    {
        "ID": 1520149,
        "Name": "重生回古代但只想当会计",
        "Popularity": 2977849.86,
        "Collection": 8457,
        "Timestamp": "2025-03-05 03:28:48"
    },
    {
        "ID": 1609999,
        "Name": "月之暗面",
        "Popularity": 840491.92,
        "Collection": 2043,
        "Timestamp": "2025-03-05 03:28:49"
    },
    {
        "ID": 1642822,
        "Name": "心动不渝",
        "Popularity": 119120.25,
        "Collection": 211,
        "Timestamp": "2025-03-05 03:28:52"
    },
    {
        "ID": 1454325,
        "Name": "浪心朝圣",
        "Popularity": 51403.43,
        "Collection": 66,
        "Timestamp": "2025-03-05 03:28:53"
    },
    {
        "ID": 1808704,
        "Name": "山神",
        "Popularity": 5832.96,
        "Collection": 8,
        "Timestamp": "2025-03-05 03:28:54"
    },
    {
        "ID": 1725082,
        "Name": "劣质春日",
        "Popularity": 499221.5,
        "Collection": 986,
        "Timestamp": "2025-03-05 03:28:55"
    },
    {
        "ID": 1786057,
        "Name": "海平面之上",
        "Popularity": 20953.65,
        "Collection": 9,
        "Timestamp": "2025-03-05 03:28:56"
    },
    {
        "ID": 1780640,
        "Name": "我们不是分手了吗",
        "Popularity": 2882620.67,
        "Collection": 6082,
        "Timestamp": "2025-03-05 03:28:57"
    },
    {
        "ID": 1780172,
        "Name": "货不对版",
        "Popularity": 164819.5,
        "Collection": 472,
        "Timestamp": "2025-03-05 03:28:58"
    },
    {
        "ID": 1770880,
        "Name": "作奸犯君",
        "Popularity": 226319.75,
        "Collection": 449,
        "Timestamp": "2025-03-05 03:28:59"
    },
    {
        "ID": 1756538,
        "Name": "爱神号沉没事件",
        "Popularity": 877757.45,
        "Collection": 1868,
        "Timestamp": "2025-03-05 03:29:00"
    },
    {
        "ID": 1734608,
        "Name": "谷雨时分",
        "Popularity": 1729031.05,
        "Collection": 5137,
        "Timestamp": "2025-03-05 03:29:01"
    },
    {
        "ID": 1723981,
        "Name": "他怎么还不和我分手",
        "Popularity": 15688543.75,
        "Collection": 17673,
        "Timestamp": "2025-03-05 03:29:03"
    },
    {
        "ID": 1569273,
        "Name": "溶解症",
        "Popularity": 4546108.12,
        "Collection": 9592,
        "Timestamp": "2025-03-05 03:29:04"
    },
    {
        "ID": 1551150,
        "Name": "狗东西",
        "Popularity": 166445.25,
        "Collection": 349,
        "Timestamp": "2025-03-05 03:29:05"
    },
    {
        "ID": 1467461,
        "Name": "他的玩臣",
        "Popularity": 1003195.5,
        "Collection": 4068,
        "Timestamp": "2025-03-05 03:29:06"
    },
    {
        "ID": 1096501,
        "Name": "太太，不可以这样",
        "Popularity": 3982973.75,
        "Collection": 7242,
        "Timestamp": "2025-03-05 03:29:07"
    },
    {
        "ID": 1470371,
        "Name": "无人管束",
        "Popularity": 8497817.58,
        "Collection": 8507,
        "Timestamp": "2025-03-05 03:29:08"
    },
    {
        "ID": 1442932,
        "Name": "月亮维修计划",
        "Popularity": 124978.66,
        "Collection": 225,
        "Timestamp": "2025-03-05 03:29:09"
    },
    {
        "ID": 1732562,
        "Name": "迷神道",
        "Popularity": 6502775.15,
        "Collection": 11477,
        "Timestamp": "2025-03-05 03:29:10"
    },
    {
        "ID": 1780671,
        "Name": "也不是很有素质",
        "Popularity": 83921.45,
        "Collection": 157,
        "Timestamp": "2025-03-05 03:29:11"
    },
    {
        "ID": 1745048,
        "Name": "我当松树那些年",
        "Popularity": 772202.33,
        "Collection": 1378,
        "Timestamp": "2025-03-05 03:29:12"
    },
    {
        "ID": 1507716,
        "Name": "冬禧民宿",
        "Popularity": 3297894.31,
        "Collection": 6843,
        "Timestamp": "2025-03-05 03:29:14"
    },
    {
        "ID": 199513,
        "Name": "你的长夏永不凋落",
        "Popularity": 336031.08,
        "Collection": 995,
        "Timestamp": "2025-03-05 03:29:15"
    },
    {
        "ID": 1303212,
        "Name": "折金枝",
        "Popularity": 4296237.67,
        "Collection": 7762,
        "Timestamp": "2025-03-05 03:29:16"
    },
    {
        "ID": 1679774,
        "Name": "求佛",
        "Popularity": 306570.78,
        "Collection": 636,
        "Timestamp": "2025-03-05 03:29:17"
    },
    {
        "ID": 1773521,
        "Name": "共生荆棘",
        "Popularity": 36069.79,
        "Collection": 16,
        "Timestamp": "2025-03-05 03:29:18"
    },
    {
        "ID": 1369351,
        "Name": "偏见与偏爱",
        "Popularity": 392226.6,
        "Collection": 552,
        "Timestamp": "2025-03-05 03:29:19"
    },
    {
        "ID": 1743194,
        "Name": "躲船船",
        "Popularity": 45941.4,
        "Collection": 100,
        "Timestamp": "2025-03-05 03:29:20"
    },
    {
        "ID": 1784654,
        "Name": "裸色",
        "Popularity": 808045.83,
        "Collection": 2141,
        "Timestamp": "2025-03-05 03:29:21"
    },
    {
        "ID": 1702053,
        "Name": "见不得光的",
        "Popularity": 2327187.36,
        "Collection": 3488,
        "Timestamp": "2025-03-05 03:29:21"
    },
    {
        "ID": 1773122,
        "Name": "好命",
        "Popularity": 76743.59,
        "Collection": 207,
        "Timestamp": "2025-03-05 03:29:22"
    },
    {
        "ID": 1799711,
        "Name": "去南加",
        "Popularity": 61210.25,
        "Collection": 57,
        "Timestamp": "2025-03-05 03:29:24"
    },
    {
        "ID": 1501904,
        "Name": "好梦发生",
        "Popularity": 941342.14,
        "Collection": 1803,
        "Timestamp": "2025-03-05 03:29:26"
    },
    {
        "ID": 1725720,
        "Name": "谎话仙",
        "Popularity": 120279.6,
        "Collection": 167,
        "Timestamp": "2025-03-05 03:29:27"
    },
    {
        "ID": 1739326,
        "Name": "竹马成双",
        "Popularity": 103731.25,
        "Collection": 192,
        "Timestamp": "2025-03-05 03:29:28"
    },
    {
        "ID": 1142976,
        "Name": "反派和狙击手",
        "Popularity": 13910589.29,
        "Collection": 50170,
        "Timestamp": "2025-03-05 03:29:28"
    },
    {
        "ID": 1511831,
        "Name": "限定暧昧",
        "Popularity": 564707.64,
        "Collection": 1167,
        "Timestamp": "2025-03-05 03:29:29"
    },
    {
        "ID": 456197,
        "Name": "反骨",
        "Popularity": 9814156.85,
        "Collection": 29658,
        "Timestamp": "2025-03-05 03:29:31"
    },
    {
        "ID": 1570931,
        "Name": "白月光手册",
        "Popularity": 33508.91,
        "Collection": 28,
        "Timestamp": "2025-03-05 03:29:32"
    },
    {
        "ID": 1632354,
        "Name": "所以尸体会自己系鞋带吗",
        "Popularity": 596227.76,
        "Collection": 1895,
        "Timestamp": "2025-03-05 03:29:33"
    },
    {
        "ID": 1254218,
        "Name": "爱河遗珠",
        "Popularity": 33888.38,
        "Collection": 211,
        "Timestamp": "2025-03-05 03:29:34"
    },
    {
        "ID": 1816268,
        "Name": "五夜",
        "Popularity": 5282.88,
        "Collection": 9,
        "Timestamp": "2025-03-05 03:29:36"
    },
    {
        "ID": 1604795,
        "Name": "皆大欢喜",
        "Popularity": 215209.4,
        "Collection": 168,
        "Timestamp": "2025-03-05 03:29:37"
    },
    {
        "ID": 1626628,
        "Name": "夏日戒断",
        "Popularity": 296737.19,
        "Collection": 545,
        "Timestamp": "2025-03-05 03:29:38"
    },
    {
        "ID": 1795135,
        "Name": "溯流",
        "Popularity": 17087.12,
        "Collection": 12,
        "Timestamp": "2025-03-05 03:29:39"
    },
    {
        "ID": 1315188,
        "Name": "与我沉溺",
        "Popularity": 1070624.61,
        "Collection": 3373,
        "Timestamp": "2025-03-05 03:29:40"
    },
    {
        "ID": 1502126,
        "Name": "全校传我们不合",
        "Popularity": 3919986.66,
        "Collection": 7579,
        "Timestamp": "2025-03-05 03:29:40"
    },
    {
        "ID": 1470310,
        "Name": "从一而终",
        "Popularity": 53279.02,
        "Collection": 175,
        "Timestamp": "2025-03-05 03:29:41"
    },
    {
        "ID": 1785384,
        "Name": "逐星",
        "Popularity": 31003.25,
        "Collection": 17,
        "Timestamp": "2025-03-05 03:29:43"
    },
    {
        "ID": 1565269,
        "Name": "重启一下",
        "Popularity": 73031.25,
        "Collection": 106,
        "Timestamp": "2025-03-05 03:29:43"
    },
    {
        "ID": 1724471,
        "Name": "水杉枝",
        "Popularity": 1868.25,
        "Collection": 6,
        "Timestamp": "2025-03-05 03:29:44"
    },
    {
        "ID": 1524917,
        "Name": "别猜了，我弯的",
        "Popularity": 1443504.44,
        "Collection": 6263,
        "Timestamp": "2025-03-05 03:29:46"
    },
    {
        "ID": 1517079,
        "Name": "晨与晖",
        "Popularity": 1062406.96,
        "Collection": 1190,
        "Timestamp": "2025-03-05 03:29:47"
    },
    {
        "ID": 1456750,
        "Name": "职业拾荒",
        "Popularity": 149241.5,
        "Collection": 320,
        "Timestamp": "2025-03-05 03:29:48"
    },
    {
        "ID": 1672452,
        "Name": "镁光灯与机械臂",
        "Popularity": 221529.1,
        "Collection": 269,
        "Timestamp": "2025-03-05 03:29:49"
    },
    {
        "ID": 1772407,
        "Name": "奸党",
        "Popularity": 180469.07,
        "Collection": 91,
        "Timestamp": "2025-03-05 03:29:50"
    },
    {
        "ID": 1728462,
        "Name": "开太平",
        "Popularity": 54556.7,
        "Collection": 48,
        "Timestamp": "2025-03-05 03:29:51"
    },
    {
        "ID": 929879,
        "Name": "丹青为鉴",
        "Popularity": 590397.72,
        "Collection": 1054,
        "Timestamp": "2025-03-05 03:29:52"
    },
    {
        "ID": 1815534,
        "Name": "故剑",
        "Popularity": 14903.25,
        "Collection": 17,
        "Timestamp": "2025-03-05 03:29:53"
    },
    {
        "ID": 1753992,
        "Name": "末日公路",
        "Popularity": 24752.25,
        "Collection": 23,
        "Timestamp": "2025-03-05 03:29:54"
    },
    {
        "ID": 1498628,
        "Name": "贪心无厌",
        "Popularity": 567883.5,
        "Collection": 1364,
        "Timestamp": "2025-03-05 03:29:55"
    },
    {
        "ID": 457888,
        "Name": "他乡遇顾栀",
        "Popularity": 86662.95,
        "Collection": 90,
        "Timestamp": "2025-03-05 03:29:57"
    },
    {
        "ID": 1614876,
        "Name": "嗅觉依赖",
        "Popularity": 1957664.04,
        "Collection": 4888,
        "Timestamp": "2025-03-05 03:29:58"
    },
    {
        "ID": 1773200,
        "Name": "撞见",
        "Popularity": 96482.9,
        "Collection": 173,
        "Timestamp": "2025-03-05 03:29:58"
    },
    {
        "ID": 1752341,
        "Name": "爱情过滤理论",
        "Popularity": 57844.5,
        "Collection": 63,
        "Timestamp": "2025-03-05 03:29:59"
    },
    {
        "ID": 1453512,
        "Name": "漂亮死对头反攻我",
        "Popularity": 3247405.83,
        "Collection": 5792,
        "Timestamp": "2025-03-05 03:30:00"
    },
    {
        "ID": 1779018,
        "Name": "极端天气",
        "Popularity": 60253.5,
        "Collection": 172,
        "Timestamp": "2025-03-05 03:30:01"
    },
    {
        "ID": 1785541,
        "Name": "半熟",
        "Popularity": 159999,
        "Collection": 363,
        "Timestamp": "2025-03-05 03:30:02"
    },
    {
        "ID": 1807169,
        "Name": "做你的梦",
        "Popularity": 17340.02,
        "Collection": 82,
        "Timestamp": "2025-03-05 03:30:03"
    },
    {
        "ID": 1644976,
        "Name": "强制匹配",
        "Popularity": 250017.25,
        "Collection": 491,
        "Timestamp": "2025-03-05 03:30:05"
    },
    {
        "ID": 1721641,
        "Name": "别有所图",
        "Popularity": 17197.76,
        "Collection": 11,
        "Timestamp": "2025-03-05 03:30:06"
    },
    {
        "ID": 1799810,
        "Name": "上青天",
        "Popularity": 8241.75,
        "Collection": 7,
        "Timestamp": "2025-03-05 03:30:08"
    },
    {
        "ID": 1004738,
        "Name": "今夜不言",
        "Popularity": 320605.67,
        "Collection": 939,
        "Timestamp": "2025-03-05 03:30:09"
    },
    {
        "ID": 1518112,
        "Name": "乔右的一天",
        "Popularity": 86805.93,
        "Collection": 402,
        "Timestamp": "2025-03-05 03:30:10"
    },
    {
        "ID": 1810775,
        "Name": "如火止沸",
        "Popularity": 67982.15,
        "Collection": 97,
        "Timestamp": "2025-03-05 03:30:10"
    },
    {
        "ID": 1693366,
        "Name": "难登天",
        "Popularity": 94609.62,
        "Collection": 529,
        "Timestamp": "2025-03-05 03:30:11"
    },
    {
        "ID": 1785928,
        "Name": "流浪狗",
        "Popularity": 21952.5,
        "Collection": 7,
        "Timestamp": "2025-03-05 03:30:12"
    },
    {
        "ID": 1743123,
        "Name": "斗鲨",
        "Popularity": 2413179.43,
        "Collection": 3573,
        "Timestamp": "2025-03-05 03:30:13"
    },
    {
        "ID": 1688759,
        "Name": "论直男是如何掰弯自己的",
        "Popularity": 130254.5,
        "Collection": 212,
        "Timestamp": "2025-03-05 03:30:14"
    },
    {
        "ID": 1522798,
        "Name": "为时已晚",
        "Popularity": 221138,
        "Collection": 1097,
        "Timestamp": "2025-03-05 03:30:15"
    },
    {
        "ID": 1470596,
        "Name": "津枫港遗事",
        "Popularity": 621400.75,
        "Collection": 1815,
        "Timestamp": "2025-03-05 03:30:16"
    },
    {
        "ID": 1464040,
        "Name": "狐宠",
        "Popularity": 546768,
        "Collection": 1467,
        "Timestamp": "2025-03-05 03:30:18"
    },
    {
        "ID": 1374045,
        "Name": "启明摇篮",
        "Popularity": 275613.26,
        "Collection": 528,
        "Timestamp": "2025-03-05 03:30:19"
    },
    {
        "ID": 1326635,
        "Name": "刺杀主唱",
        "Popularity": 380821.5,
        "Collection": 837,
        "Timestamp": "2025-03-05 03:30:20"
    },
    {
        "ID": 693794,
        "Name": "月老的冥婚业务",
        "Popularity": 252769.49,
        "Collection": 1144,
        "Timestamp": "2025-03-05 03:30:21"
    },
    {
        "ID": 1788739,
        "Name": "姻缘线",
        "Popularity": 27667.75,
        "Collection": 5,
        "Timestamp": "2025-03-05 03:30:21"
    },
    {
        "ID": 1686348,
        "Name": "看到你了",
        "Popularity": 558205.45,
        "Collection": 2226,
        "Timestamp": "2025-03-05 03:30:22"
    },
    {
        "ID": 1761778,
        "Name": "便宜替身",
        "Popularity": 134887.37,
        "Collection": 284,
        "Timestamp": "2025-03-05 03:30:23"
    },
    {
        "ID": 1634084,
        "Name": "冷冰冰和哭唧唧",
        "Popularity": 3698847.24,
        "Collection": 7302,
        "Timestamp": "2025-03-05 03:30:24"
    },
    {
        "ID": 1518857,
        "Name": "酩酊不醒",
        "Popularity": 12506711.28,
        "Collection": 23858,
        "Timestamp": "2025-03-05 03:30:25"
    },
    {
        "ID": 1719852,
        "Name": "引火安身",
        "Popularity": 54737.44,
        "Collection": 138,
        "Timestamp": "2025-03-05 03:30:26"
    },
    {
        "ID": 1650377,
        "Name": "祈愿碑",
        "Popularity": 1741563.89,
        "Collection": 4429,
        "Timestamp": "2025-03-05 03:30:28"
    },
    {
        "ID": 1693488,
        "Name": "沧浪君",
        "Popularity": 9631.17,
        "Collection": 22,
        "Timestamp": "2025-03-05 03:30:29"
    },
    {
        "ID": 1744894,
        "Name": "扑街偶像剧指北",
        "Popularity": 1120059.19,
        "Collection": 1132,
        "Timestamp": "2025-03-05 03:30:30"
    },
    {
        "ID": 1641250,
        "Name": "门客",
        "Popularity": 381786.9,
        "Collection": 772,
        "Timestamp": "2025-03-05 03:30:31"
    },
    {
        "ID": 1287285,
        "Name": "幽灵旅行者",
        "Popularity": 202750.35,
        "Collection": 312,
        "Timestamp": "2025-03-05 03:30:31"
    },
    {
        "ID": 1768751,
        "Name": "被死后的竹马探班了",
        "Popularity": 129221.15,
        "Collection": 470,
        "Timestamp": "2025-03-05 03:30:32"
    },
    {
        "ID": 1809008,
        "Name": "关于我喜欢你这件小事",
        "Popularity": 18279.79,
        "Collection": 12,
        "Timestamp": "2025-03-05 03:30:33"
    },
    {
        "ID": 1282243,
        "Name": "消愁",
        "Popularity": 56416.98,
        "Collection": 143,
        "Timestamp": "2025-03-05 03:30:34"
    },
    {
        "ID": 1488737,
        "Name": "前夫哥",
        "Popularity": 6292.38,
        "Collection": 8,
        "Timestamp": "2025-03-05 03:30:35"
    },
    {
        "ID": 1578825,
        "Name": "碧色荒漠",
        "Popularity": 1256572.47,
        "Collection": 2673,
        "Timestamp": "2025-03-05 03:30:36"
    },
    {
        "ID": 1731681,
        "Name": "枝上蔷薇",
        "Popularity": 141000.42,
        "Collection": 256,
        "Timestamp": "2025-03-05 03:30:38"
    },
    {
        "ID": 1699185,
        "Name": "善养",
        "Popularity": 2071266.28,
        "Collection": 3471,
        "Timestamp": "2025-03-05 03:30:39"
    },
    {
        "ID": 1101179,
        "Name": "歧途",
        "Popularity": 1146100.45,
        "Collection": 1637,
        "Timestamp": "2025-03-05 03:30:40"
    },
    {
        "ID": 1769613,
        "Name": "狐狸下山日常",
        "Popularity": 11130.25,
        "Collection": 13,
        "Timestamp": "2025-03-05 03:30:41"
    },
    {
        "ID": 1773213,
        "Name": "极夜南星",
        "Popularity": 68948.69,
        "Collection": 116,
        "Timestamp": "2025-03-05 03:30:42"
    },
    {
        "ID": 1798393,
        "Name": "酹酒",
        "Popularity": 11423.25,
        "Collection": 4,
        "Timestamp": "2025-03-05 03:30:42"
    },
    {
        "ID": 1742897,
        "Name": "鸢尾王座",
        "Popularity": 143782.5,
        "Collection": 160,
        "Timestamp": "2025-03-05 03:30:43"
    },
    {
        "ID": 1739813,
        "Name": "蓝色漩涡",
        "Popularity": 395547,
        "Collection": 125,
        "Timestamp": "2025-03-05 03:30:44"
    },
    {
        "ID": 1704451,
        "Name": "我就不行么",
        "Popularity": 820623.82,
        "Collection": 1527,
        "Timestamp": "2025-03-05 03:30:45"
    },
    {
        "ID": 1647451,
        "Name": "明日心想事成",
        "Popularity": 2272766.5,
        "Collection": 4621,
        "Timestamp": "2025-03-05 03:30:46"
    },
    {
        "ID": 1346880,
        "Name": "头七见魂",
        "Popularity": 2780894.93,
        "Collection": 5169,
        "Timestamp": "2025-03-05 03:30:48"
    },
    {
        "ID": 276793,
        "Name": "飞鸟与荆棘",
        "Popularity": 87411.25,
        "Collection": 156,
        "Timestamp": "2025-03-05 03:30:49"
    },
    {
        "ID": 1573878,
        "Name": "双向驯服",
        "Popularity": 198638.13,
        "Collection": 483,
        "Timestamp": "2025-03-05 03:30:49"
    },
    {
        "ID": 1367690,
        "Name": "未晚",
        "Popularity": 4006870.73,
        "Collection": 6622,
        "Timestamp": "2025-03-05 03:30:50"
    },
    {
        "ID": 1605586,
        "Name": "崇西长眠",
        "Popularity": 95448.5,
        "Collection": 262,
        "Timestamp": "2025-03-05 03:30:51"
    },
    {
        "ID": 1483031,
        "Name": "伏鳞歌",
        "Popularity": 164663.75,
        "Collection": 265,
        "Timestamp": "2025-03-05 03:30:52"
    },
    {
        "ID": 1444053,
        "Name": "一衿香",
        "Popularity": 3130934.75,
        "Collection": 4414,
        "Timestamp": "2025-03-05 03:30:53"
    },
    {
        "ID": 1673072,
        "Name": "老攻的食用攻略",
        "Popularity": 500687.25,
        "Collection": 1089,
        "Timestamp": "2025-03-05 03:30:54"
    },
    {
        "ID": 1785103,
        "Name": "虚度的夏日",
        "Popularity": 92978.25,
        "Collection": 96,
        "Timestamp": "2025-03-05 03:30:55"
    },
    {
        "ID": 1747916,
        "Name": "未定义与命名",
        "Popularity": 199057.25,
        "Collection": 265,
        "Timestamp": "2025-03-05 03:30:56"
    },
    {
        "ID": 1808495,
        "Name": "骑士甲和他的精灵王子",
        "Popularity": 4105,
        "Collection": 4,
        "Timestamp": "2025-03-05 03:30:58"
    },
    {
        "ID": 1301220,
        "Name": "碾压",
        "Popularity": 216180.25,
        "Collection": 384,
        "Timestamp": "2025-03-05 03:30:58"
    },
    {
        "ID": 1787635,
        "Name": "兔子与颠茄",
        "Popularity": 50059.5,
        "Collection": 73,
        "Timestamp": "2025-03-05 03:30:59"
    },
    {
        "ID": 1750739,
        "Name": "试情",
        "Popularity": 47979.5,
        "Collection": 223,
        "Timestamp": "2025-03-05 03:31:00"
    },
    {
        "ID": 1771968,
        "Name": "南辕北辙",
        "Popularity": 20346.5,
        "Collection": 20,
        "Timestamp": "2025-03-05 03:31:01"
    },
    {
        "ID": 1781351,
        "Name": "深渊回响",
        "Popularity": 371449.75,
        "Collection": 755,
        "Timestamp": "2025-03-05 03:31:02"
    },
    {
        "ID": 1642596,
        "Name": "孔雀饲养指南",
        "Popularity": 441229.25,
        "Collection": 1025,
        "Timestamp": "2025-03-05 03:31:03"
    },
    {
        "ID": 1619320,
        "Name": "南洋往事",
        "Popularity": 57229.76,
        "Collection": 274,
        "Timestamp": "2025-03-05 03:31:04"
    },
    {
        "ID": 328490,
        "Name": "为我所用",
        "Popularity": 2892110.5,
        "Collection": 3917,
        "Timestamp": "2025-03-05 03:31:05"
    },
    {
        "ID": 1759146,
        "Name": "旧恩",
        "Popularity": 251664,
        "Collection": 520,
        "Timestamp": "2025-03-05 03:31:06"
    },
    {
        "ID": 1768678,
        "Name": "长生",
        "Popularity": 69346.5,
        "Collection": 70,
        "Timestamp": "2025-03-05 03:31:08"
    },
    {
        "ID": 1814538,
        "Name": "深海狩猎",
        "Popularity": 26157.25,
        "Collection": 35,
        "Timestamp": "2025-03-05 03:31:08"
    },
    {
        "ID": 1304884,
        "Name": "夏日感冒",
        "Popularity": 411021.63,
        "Collection": 1603,
        "Timestamp": "2025-03-05 03:31:09"
    },
    {
        "ID": 1727727,
        "Name": "樊青",
        "Popularity": 4237847.5,
        "Collection": 5838,
        "Timestamp": "2025-03-05 03:31:10"
    },
    {
        "ID": 988484,
        "Name": "三千零一夜",
        "Popularity": 786258.5,
        "Collection": 1718,
        "Timestamp": "2025-03-05 03:31:11"
    },
    {
        "ID": 1601770,
        "Name": "不死鸟的终末",
        "Popularity": 1015164.75,
        "Collection": 2079,
        "Timestamp": "2025-03-05 03:31:12"
    },
    {
        "ID": 145179,
        "Name": "残响",
        "Popularity": 325049,
        "Collection": 950,
        "Timestamp": "2025-03-05 03:31:13"
    },
    {
        "ID": 1713326,
        "Name": "降雪时分",
        "Popularity": 442102,
        "Collection": 769,
        "Timestamp": "2025-03-05 03:31:14"
    },
    {
        "ID": 1808954,
        "Name": "于心有愧",
        "Popularity": 114765.73,
        "Collection": 155,
        "Timestamp": "2025-03-05 03:31:15"
    },
    {
        "ID": 1511418,
        "Name": "弥留之际",
        "Popularity": 35520.41,
        "Collection": 18,
        "Timestamp": "2025-03-05 03:31:16"
    },
    {
        "ID": 1667642,
        "Name": "溶金",
        "Popularity": 7074143.75,
        "Collection": 6837,
        "Timestamp": "2025-03-05 03:31:18"
    },
    {
        "ID": 1586092,
        "Name": "漫长雨季",
        "Popularity": 7257141.04,
        "Collection": 9488,
        "Timestamp": "2025-03-05 03:31:19"
    },
    {
        "ID": 1680563,
        "Name": "德老大今天喝酸奶了吗",
        "Popularity": 1320091.65,
        "Collection": 2948,
        "Timestamp": "2025-03-05 03:31:20"
    },
    {
        "ID": 1669288,
        "Name": "你才不是我爹！",
        "Popularity": 55446.68,
        "Collection": 40,
        "Timestamp": "2025-03-05 03:31:21"
    },
    {
        "ID": 232341,
        "Name": "明知做戏",
        "Popularity": 477305.5,
        "Collection": 943,
        "Timestamp": "2025-03-05 03:31:21"
    },
    {
        "ID": 231705,
        "Name": "大逃杀",
        "Popularity": 3165710.25,
        "Collection": 5276,
        "Timestamp": "2025-03-05 03:31:22"
    },
    {
        "ID": 1767788,
        "Name": "此间禁止飞行",
        "Popularity": 114446.75,
        "Collection": 61,
        "Timestamp": "2025-03-05 03:31:23"
    },
    {
        "ID": 1448266,
        "Name": "赵明志的盼望",
        "Popularity": 33824.75,
        "Collection": 40,
        "Timestamp": "2025-03-05 03:31:24"
    },
    {
        "ID": 1377901,
        "Name": "车魂",
        "Popularity": 91042,
        "Collection": 359,
        "Timestamp": "2025-03-05 03:31:25"
    },
    {
        "ID": 1739607,
        "Name": "骑驴列过孤独星球",
        "Popularity": 1348919,
        "Collection": 1335,
        "Timestamp": "2025-03-05 03:31:26"
    },
    {
        "ID": 1755450,
        "Name": "连理枝",
        "Popularity": 3510602.5,
        "Collection": 7093,
        "Timestamp": "2025-03-05 03:31:28"
    },
    {
        "ID": 1211785,
        "Name": "岁陈楠下",
        "Popularity": 442934.75,
        "Collection": 1330,
        "Timestamp": "2025-03-05 03:31:29"
    },
    {
        "ID": 1756518,
        "Name": "贝勃定律",
        "Popularity": 1555821.25,
        "Collection": 2957,
        "Timestamp": "2025-03-05 03:31:30"
    },
    {
        "ID": 1789549,
        "Name": "迟早还债",
        "Popularity": 87733.25,
        "Collection": 201,
        "Timestamp": "2025-03-05 03:31:31"
    },
    {
        "ID": 1767687,
        "Name": "先吃饭吧",
        "Popularity": 149680.25,
        "Collection": 227,
        "Timestamp": "2025-03-05 03:31:32"
    },
    {
        "ID": 1670671,
        "Name": "戒烟",
        "Popularity": 4020709.4,
        "Collection": 9738,
        "Timestamp": "2025-03-05 03:31:33"
    },
    {
        "ID": 1760075,
        "Name": "一梦黄粱",
        "Popularity": 84142.5,
        "Collection": 36,
        "Timestamp": "2025-03-05 03:31:33"
    },
    {
        "ID": 1214363,
        "Name": "水母游过夏天",
        "Popularity": 9153347.25,
        "Collection": 10715,
        "Timestamp": "2025-03-05 03:31:34"
    },
    {
        "ID": 1751307,
        "Name": "灰羽衣仙子",
        "Popularity": 447550.25,
        "Collection": 614,
        "Timestamp": "2025-03-05 03:31:35"
    },
    {
        "ID": 1492742,
        "Name": "小苏快过桥",
        "Popularity": 476590.5,
        "Collection": 902,
        "Timestamp": "2025-03-05 03:31:36"
    },
    {
        "ID": 1685775,
        "Name": "不当大哥",
        "Popularity": 296110.5,
        "Collection": 546,
        "Timestamp": "2025-03-05 03:31:38"
    },
    {
        "ID": 1772035,
        "Name": "我心昭昭",
        "Popularity": 11840.75,
        "Collection": 24,
        "Timestamp": "2025-03-05 03:31:39"
    },
    {
        "ID": 1511025,
        "Name": "月渡平野",
        "Popularity": 1472168.75,
        "Collection": 3060,
        "Timestamp": "2025-03-05 03:31:40"
    },
    {
        "ID": 1629274,
        "Name": "碎玉劫",
        "Popularity": 2116507.5,
        "Collection": 2360,
        "Timestamp": "2025-03-05 03:31:41"
    },
    {
        "ID": 1222324,
        "Name": "折骨为臣",
        "Popularity": 9681314.25,
        "Collection": 13129,
        "Timestamp": "2025-03-05 03:31:42"
    },
    {
        "ID": 1750711,
        "Name": "延迟恋爱",
        "Popularity": 54622.25,
        "Collection": 55,
        "Timestamp": "2025-03-05 03:31:43"
    },
    {
        "ID": 1183716,
        "Name": "你是不是有别的小鸟了",
        "Popularity": 1123405.75,
        "Collection": 3265,
        "Timestamp": "2025-03-05 03:31:43"
    },
    {
        "ID": 1729264,
        "Name": "我和储备粮的赛博童话",
        "Popularity": 22731.5,
        "Collection": 24,
        "Timestamp": "2025-03-05 03:31:44"
    },
    {
        "ID": 1770935,
        "Name": "浮尘",
        "Popularity": 68973,
        "Collection": 103,
        "Timestamp": "2025-03-05 03:31:45"
    },
    {
        "ID": 1547194,
        "Name": "八卦",
        "Popularity": 727977.28,
        "Collection": 1489,
        "Timestamp": "2025-03-05 03:31:46"
    },
    {
        "ID": 1721631,
        "Name": "私相受受",
        "Popularity": 16144435.75,
        "Collection": 11821,
        "Timestamp": "2025-03-05 03:31:48"
    },
    {
        "ID": 1570989,
        "Name": "请仙尊做客",
        "Popularity": 156183.98,
        "Collection": 548,
        "Timestamp": "2025-03-05 03:31:49"
    },
    {
        "ID": 1794214,
        "Name": "犬齿与面包",
        "Popularity": 15354.95,
        "Collection": 11,
        "Timestamp": "2025-03-05 03:31:50"
    },
    {
        "ID": 1249382,
        "Name": "不渡",
        "Popularity": 114378.79,
        "Collection": 333,
        "Timestamp": "2025-03-05 03:31:51"
    },
    {
        "ID": 1735608,
        "Name": "半进口热恋",
        "Popularity": 73404.73,
        "Collection": 59,
        "Timestamp": "2025-03-05 03:31:51"
    },
    {
        "ID": 1747364,
        "Name": "追雁计划",
        "Popularity": 26251.5,
        "Collection": 3,
        "Timestamp": "2025-03-05 03:31:52"
    },
    {
        "ID": 1604456,
        "Name": "秋收",
        "Popularity": 203973.25,
        "Collection": 363,
        "Timestamp": "2025-03-05 03:31:53"
    },
    {
        "ID": 1762548,
        "Name": "兔子来信",
        "Popularity": 32867,
        "Collection": 31,
        "Timestamp": "2025-03-05 03:31:54"
    },
    {
        "ID": 1492028,
        "Name": "脏东西",
        "Popularity": 36792731.5,
        "Collection": 28007,
        "Timestamp": "2025-03-05 03:31:55"
    },
    {
        "ID": 1775047,
        "Name": "暂别309日",
        "Popularity": 32688,
        "Collection": 56,
        "Timestamp": "2025-03-05 03:31:56"
    }
]