[
    {
        "ID": 1706847,
        "Name": "他怎么可能暗恋我",
        "Popularity": 6085304,
        "Collection": 7672,
        "Timestamp": "2025-03-05 03:31:58"
    },
    {
        "ID": 1665113,
        "Name": "瘾欲",
        "Popularity": 8080944,
        "Collection": 7745,
        "Timestamp": "2025-03-05 03:31:58"
    },
    {
        "ID": 1667642,
        "Name": "溶金",
        "Popularity": 7074083,
        "Collection": 6837,
        "Timestamp": "2025-03-05 03:31:58"
    },
    {
        "ID": 1470260,
        "Name": "落星",
        "Popularity": 3305448,
        "Collection": 7846,
        "Timestamp": "2025-03-05 03:31:58"
    },
    {
        "ID": 1755450,
        "Name": "连理枝",
        "Popularity": 3510452,
        "Collection": 7092,
        "Timestamp": "2025-03-05 03:31:58"
    },
    {
        "ID": 1731402,
        "Name": "隐燃",
        "Popularity": 4648301,
        "Collection": 5896,
        "Timestamp": "2025-03-05 03:31:58"
    },
    {
        "ID": 1665468,
        "Name": "伴青",
        "Popularity": 3222999,
        "Collection": 5610,
        "Timestamp": "2025-03-05 03:31:58"
    },
    {
        "ID": 1704555,
        "Name": "离婚快乐",
        "Popularity": 2702689,
        "Collection": 4458,
        "Timestamp": "2025-03-05 03:31:58"
    }
]